imapdedup/__init__.py
imapdedup/imapdedup.py
imapdedup-1.2.dist-info/METADATA
imapdedup-1.2.dist-info/WHEEL
imapdedup-1.2.dist-info/entry_points.txt
imapdedup-1.2.dist-info/licenses/LICENCE.TXT
imapdedup-1.2.dist-info/RECORD
