Metadata-Version: 2.3
Name: imapdedup
Version: 1.2
Summary: IMAP de-duplication tool
Requires-Python: >=3.6
